ntn_torch/__init__.py
ntn_torch/encodings.py
ntn_torch/net.py
ntn_torch/rl/__init__.py
ntn_torch/rl/common/__init__.py
ntn_torch/rl/common/buffers.py
ntn_torch/rl/common/extractors.py
ntn_torch/rl/common/plot_util.py
ntn_torch/rl/common/policies.py
ntn_torch/rl/common/utils.py
ntn_torch/rl/ntn_reinforce/__init__.py
ntn_torch/rl/ntn_reinforce/ntn_reinforce.py
ntn_torch/rl/reinforce/__init__.py
ntn_torch/rl/reinforce/reinforce.py
ntn_torch/utils.py
ntn_torch-0.3.3.dist-info/WHEEL
ntn_torch-0.3.3.dist-info/METADATA
ntn_torch-0.3.3.dist-info/RECORD
